odoo9_addon_l10n_be_mis_reports-9.0.1.1.0-py2.7-nspkg.pth
odoo9_addon_l10n_be_mis_reports-9.0.1.1.0.dist-info/DESCRIPTION.rst
odoo9_addon_l10n_be_mis_reports-9.0.1.1.0.dist-info/METADATA
odoo9_addon_l10n_be_mis_reports-9.0.1.1.0.dist-info/RECORD
odoo9_addon_l10n_be_mis_reports-9.0.1.1.0.dist-info/WHEEL
odoo9_addon_l10n_be_mis_reports-9.0.1.1.0.dist-info/metadata.json
odoo9_addon_l10n_be_mis_reports-9.0.1.1.0.dist-info/namespace_packages.txt
odoo9_addon_l10n_be_mis_reports-9.0.1.1.0.dist-info/top_level.txt
odoo_addons/l10n_be_mis_reports/README.rst
odoo_addons/l10n_be_mis_reports/__init__.py
odoo_addons/l10n_be_mis_reports/__openerp__.py
odoo_addons/l10n_be_mis_reports/data/mis_report_bs.xml
odoo_addons/l10n_be_mis_reports/data/mis_report_pl.xml
odoo_addons/l10n_be_mis_reports/data/mis_report_styles.xml
odoo_addons/l10n_be_mis_reports/data/mis_report_vat.xml
odoo_addons/l10n_be_mis_reports/i18n/fr.po
odoo_addons/l10n_be_mis_reports/i18n/nl.po
