Metadata-Version: 2.0
Name: odoo9-addon-l10n-be-mis-reports
Version: 9.0.1.1.0
Summary: MIS Builder templates for the Belgium P&L and Balance Sheets
Home-page: http://acsone.eu
Author: ACSONE SA/NV,Odoo Community Association (OCA)
Author-email: support@odoo-community.org
License: AGPL-3
Platform: UNKNOWN
Classifier: Programming Language :: Python
Classifier: Framework :: Odoo
Classifier: License :: OSI Approved :: GNU Affero General Public License v3
Requires-Python: ~=2.7
Requires-Dist: odoo (<9.1a,>=9.0a)
Requires-Dist: odoo9-addon-mis-builder
